cautiousrobot/__about__.py
cautiousrobot/__init__.py
cautiousrobot/__main__.py
cautiousrobot/buddy_check.py
cautiousrobot/download.py
cautiousrobot/exceptions.py
cautiousrobot/utils.py
cautious_robot-2.0.0.dist-info/METADATA
cautious_robot-2.0.0.dist-info/WHEEL
cautious_robot-2.0.0.dist-info/entry_points.txt
cautious_robot-2.0.0.dist-info/licenses/LICENSE
cautious_robot-2.0.0.dist-info/RECORD
