Metadata-Version: 2.4
Name: cautious-robot
Version: 2.0.0
Summary: Simple downloader that downloads images from URLs in a CSV and names them by the given column. Then uses sum-buddy to gather and record checksums for all downloaded images.
Project-URL: Homepage, https://github.com/Imageomics/cautious-robot
Project-URL: Repository, https://github.com/Imageomics/cautious-robot.git
Project-URL: Bug Tracker, https://github.com/Imageomics/cautious-robot/issues
Author-email: "Elizabeth G. Campolongo" <e.campolongo479@gmail.com>
License-File: LICENSE
Classifier: License :: OSI Approved :: MIT License
Classifier: Operating System :: OS Independent
Classifier: Programming Language :: Python :: 3
Requires-Python: >=3.10
Requires-Dist: argparse
Requires-Dist: pandas
Requires-Dist: pillow
Requires-Dist: requests
Requires-Dist: sum-buddy
Provides-Extra: dev
Requires-Dist: pre-commit; extra == 'dev'
Requires-Dist: pytest; extra == 'dev'
Requires-Dist: ruff; extra == 'dev'
Provides-Extra: keywords
Requires-Dist: checksums; extra == 'keywords'
Requires-Dist: csv; extra == 'keywords'
Requires-Dist: download; extra == 'keywords'
Requires-Dist: downloader; extra == 'keywords'
Requires-Dist: downsized; extra == 'keywords'
Requires-Dist: imageomics; extra == 'keywords'
Requires-Dist: images; extra == 'keywords'
Requires-Dist: metadata; extra == 'keywords'
Requires-Dist: sequential; extra == 'keywords'
Requires-Dist: sum-buddy; extra == 'keywords'
Requires-Dist: url; extra == 'keywords'
Requires-Dist: verifier; extra == 'keywords'
